{
  "headers": {
    "etag": "\"a8a068849b0abdac8ee4b5d00a2d93bd\"",
    "x-amz-request-id": "5Q2K6JBPBQAVBQ9J",
    "set-cookie": "__cfduid=d8a94b9eb5a91924da1681b627d77d5101601177253; expires=Tue, 27-Oct-20 03:27:33 GMT; path=/; domain=.deno.land; HttpOnly; SameSite=Lax; Secure",
    "x-amz-version-id": "3Uk1jaPvGVU8oHxqbEZWsECcQxBxC9SY",
    "cache-control": "public, max-age=31536000, immutable",
    "expect-ct": "max-age=604800, report-uri=\"https://report-uri.cloudflare.com/cdn-cgi/beacon/expect-ct\"",
    "age": "62815",
    "alt-svc": "h3-27=\":443\"; ma=86400, h3-28=\":443\"; ma=86400, h3-29=\":443\"; ma=86400",
    "access-control-allow-origin": "*",
    "cf-request-id": "056f330d8c0000e5bf26140200000001",
    "date": "Sun, 27 Sep 2020 03:27:33 GMT",
    "content-length": "2027",
    "cf-cache-status": "HIT",
    "x-amz-id-2": "Q1bMEpca1GuIfYJoGGoTXb8MK3iv7ioA2l402YIVIHpmouK+n3hFSm6TTEU/74Xq8LEpNVUmbe4=",
    "vary": "Accept-Encoding",
    "server": "cloudflare",
    "last-modified": "Wed, 16 Sep 2020 00:00:17 GMT",
    "content-type": "application/typescript; charset=utf-8",
    "cf-ray": "5d922128e807e5bf-ATL",
    "accept-ranges": "bytes"
  },
  "url": "https://deno.land/x/oak@v6.2.0/mediaTyper.ts"
}