{
  "headers": {
    "x-amz-version-id": "iNU9KwhFjnxNge2hS0IKTi07scfh8qTn",
    "cf-request-id": "056f3304e00000e5bf260bd200000001",
    "content-length": "7219",
    "cf-cache-status": "HIT",
    "set-cookie": "__cfduid=d5211103753de45da0f9458e2e4280a661601177251; expires=Tue, 27-Oct-20 03:27:31 GMT; path=/; domain=.deno.land; HttpOnly; SameSite=Lax; Secure",
    "cf-ray": "5d92211b0e1ce5bf-ATL",
    "access-control-allow-origin": "*",
    "accept-ranges": "bytes",
    "age": "838857",
    "etag": "\"235b9dc659b8b6a967c825b869d12c63\"",
    "cache-control": "public, max-age=31536000, immutable",
    "x-amz-id-2": "YQo/pQliEspv3CLDJk34HChCGUNVu0ydLmBhU899T7JpxsRcKButdcZq73XUaFhiS3GBmJgd/B8=",
    "content-type": "application/typescript; charset=utf-8",
    "date": "Sun, 27 Sep 2020 03:27:31 GMT",
    "expect-ct": "max-age=604800, report-uri=\"https://report-uri.cloudflare.com/cdn-cgi/beacon/expect-ct\"",
    "last-modified": "Wed, 16 Sep 2020 00:00:17 GMT",
    "x-amz-request-id": "066F88A397A371FE",
    "vary": "Accept-Encoding",
    "server": "cloudflare",
    "alt-svc": "h3-27=\":443\"; ma=86400, h3-28=\":443\"; ma=86400, h3-29=\":443\"; ma=86400"
  },
  "url": "https://deno.land/x/oak@v6.2.0/request.ts"
}